{
  "status": 1,
  "name": "门头沟区",
  "list": [
    {
      "id": "10017Q00000000002650005",
      "heading": 0,
      "pitch": 0,
      "zoom": 1,
      "name": "鹫峰",
      "pic": "e1a871630a0d80393534315f1dc4ea1c/394002393da4c0b9ef33821f7fe8586f/10017Q00000000002650005.jpg",
      "oUrl": "http://map.qq.com/?lc=2#pano=10017Q00000000002650005&heading=293&pitch=0&zoom=1",
      "intro": "<p>。</p>",
      "map": {
        "lat": 39.880203,
        "lng": 116.410622,
        "zoom": 15
      }
    },
    {
      "id": "10017Q00000000002970006",
      "heading": 356,
      "pitch": -21,
      "zoom": 1,
      "name": "潭柘寺",
      "pic": "e1a871630a0d80393534315f1dc4ea1c/394002393da4c0b9ef33821f7fe8586f/10017Q00000000002970006.jpg",
      "oUrl": "http://map.qq.com/?lc=2#pano=10017Q00000000002970006&heading=316&pitch=6&zoom=1",
      "intro": "<p>潭柘寺位于北京西部门头沟区东南部的潭柘山麓，距市中心30余公里。寺院坐北朝南，背倚宝珠峰。潭柘寺寺内占地2.5公顷，寺外占地11.2公顷，再加上周围由潭柘寺所管辖的森林和山场，总面积达121公顷以上。</p>",
      "map": {
        "lat": 39.905150,
        "lng": 116.032260,
        "zoom": 15
      }
    },
    {
      "id": "10017Q00000000002350003",
      "heading": 283,
      "pitch": -7,
      "zoom": 1,
      "name": "白草畔",
      "pic": "e1a871630a0d80393534315f1dc4ea1c/394002393da4c0b9ef33821f7fe8586f/10017Q00000000002350003.jpg",
      "oUrl": "http://map.qq.com/?lc=2#pano=10017Q00000000002350003&heading=0&pitch=0&zoom=1",
      "intro": "<p>野三坡白草畔又称百草畔，位于河北保定市涞水县九龙镇东侧与北京的交界处，是大景区野三坡自然风景区的一部分。景区内的主峰海拔1983米，是野三坡景区内的最高峰，来到这里也以登山、观看自然风光为主。景区内有秀美的山峰怪石、茂密的森林、清泉瀑布等众多优美的自然景观，环境优美，比较精华的是高山草甸、空中花园、白桦林等景点，都可以一一探访。另外，在景区游览还可以感受和观赏一山四季、高山云海、冰川杜鹃等奇景，观赏内容十分丰富。</p>",
      "map": {
        "lat": 39.809070,
        "lng": 115.603610,
        "zoom": 13
      }
    },
    {
      "id": "10017Q00000000002950002",
      "heading": 178,
      "pitch": 14,
      "zoom": 1,
      "name": "双龙峡",
      "pic": "e1a871630a0d80393534315f1dc4ea1c/394002393da4c0b9ef33821f7fe8586f/10017Q00000000002950002.jpg",
      "oUrl": "http://map.qq.com/?lc=2#pano=10017Q00000000002950002&heading=0&pitch=0&zoom=1",
      "intro": "<p>双龙峡风景区位于京西门头沟斋堂镇火村南2、5公里距北京市区78公里。景区概括为：“十里溪流、百潭瀑布、千亩红杏、万顷林海。”真可谓青山翠谷，峰峦巍峨俊秀。到了夏季山花遍地，溪水潺潺好一派北国秀色，所以又有“小九寨”之称。</p>",
      "map": {
        "lat": 39.954010,
        "lng": 115.716880,
        "zoom": 15
      }
    },
    {
      "id": "100110Y6130706181419000",
      "heading": 322,
      "pitch": 7,
      "zoom": 1,
      "name": "石门营环岛",
      "pic": "e1a871630a0d80393534315f1dc4ea1c/394002393da4c0b9ef33821f7fe8586f/100110Y6130706181419000.jpg",
      "oUrl": "http://map.qq.com/?lc=2#pano=100110Y6130706181419000&heading=201&pitch=0&zoom=1",
      "intro": "<p>石门营公园建于2008年7月，建设面积56000平方米，其中绿地面积51000平方米。地处北京市门头沟区永定镇南部，是展示门城面貌的“门城区级休闲公园”。全年免费对群众开放。</p>",
      "map": {
        "lat": 39.894400,
        "lng": 116.108100,
        "zoom": 15
      }
    },
    {
      "id": "10017Q00000000002630005",
      "heading": 314,
      "pitch": -1,
      "zoom": 2,
      "name": "京西十八潭",
      "pic": "e1a871630a0d80393534315f1dc4ea1c/394002393da4c0b9ef33821f7fe8586f/10017Q00000000002630005.jpg",
      "oUrl": "http://map.qq.com/?lc=2#pano=10017Q00000000002630005&heading=279&pitch=5&zoom=1",
      "intro": "<p>京西十八潭位于门头沟区王平地区办事处安家庄村境内，地处海拔1528米的清水尖山峰北麓，以谷深、石奇、水特、花异而著称。</p>",
      "map": {
        "lat": 40.013960,
        "lng": 115.925400,
        "zoom": 15
      }
    },
    {
      "id": "10017Q00000000002700001",
      "heading": 307,
      "pitch": 4,
      "zoom": 1,
      "name": "灵溪风景区",
      "pic": "e1a871630a0d80393534315f1dc4ea1c/394002393da4c0b9ef33821f7fe8586f/10017Q00000000002700001.jpg",
      "oUrl": "http://map.qq.com/?lc=2#pano=10017Q00000000002700001&heading=0&pitch=0&zoom=1",
      "intro": "<p>灵溪峡谷位于北京门头沟区妙峰山风景区附近，距市区约35公里，是一片刚刚开发的自然风景区。这里山峦起伏，峡谷夹于两山之间，峡谷的尽头有一座小型水库，有小河沿峡谷流出，依地势形成一个个水潭、瀑布。两侧的山上绿树成林，山花掩映，山谷之中怪石密布，草木葱郁，流水潺潺。早春二月，漫步在峡谷里，粉红的桃花遍撒苍山，嫩绿的枝条悄悄发芽，山风轻轻扶面，鸟鸣不绝于耳，置身于一片清新与宁静之中，仿佛踏入了世外桃源。</p>",
      "map": {
        "lat": 40.018890,
        "lng": 115.978350,
        "zoom": 15
      }
    },
    {
      "id": "10017Q00000000002780003",
      "heading": 170,
      "pitch": -10,
      "zoom": 1,
      "name": "妙峰山",
      "pic": "e1a871630a0d80393534315f1dc4ea1c/394002393da4c0b9ef33821f7fe8586f/10017Q00000000002780003.jpg",
      "oUrl": "http://map.qq.com/?lc=2#pano=10017Q00000000002780003&heading=354&pitch=1&zoom=1",
      "intro": "<p>3A级旅游景区。位于北京市门头沟区妙峰山镇。109国道34公里处。距北京市区55公里，是集人文和自然风光于一体的自然风景旅游景区。妙峰山惠济祠等庙宇群始建于辽金时代，后经历次战争运动仅存少量遗址。1986年由有关部门组织重建，1988年成立景区重新对游人开放。</p>",
      "map": {
        "lat": 40.067680,
        "lng": 116.030810,
        "zoom": 15
      }
    },
    {
      "id": "10017Q00000000002600005",
      "heading": 181,
      "pitch": -4,
      "zoom": 1,
      "name": "戒台寺",
      "pic": "e1a871630a0d80393534315f1dc4ea1c/394002393da4c0b9ef33821f7fe8586f/10017Q00000000002600005.jpg",
      "oUrl": "http://map.qq.com/?lc=2#pano=10017Q00000000002600005&heading=357&pitch=-2&zoom=1",
      "intro": "<p>戒台寺位于北京市门头沟区的马鞍山上，始建于唐武德五年（公元622年），原名慧聚寺，明朝英宗皇帝赐名为万寿禅寺，因寺内建有全国最大的佛教戒坛，民间通称为戒坛寺，又叫戒台寺。戒台寺是全国重点文物保护单位，它是中国北方保存辽代文物最多、最完整的寺院。最特别的其是保留了佛塔，经幢、戒坛等辽代佛教中十分罕见的珍品。</p>",
      "map": {
        "lat": 39.871542,
        "lng": 116.087005,
        "zoom": 15
      }
    }
  ]
}
